{
  "_fv": 69,
  "_type": "recipe",
  "definition": {
    "recipeType": "Crafting",
    "recipeRetstackSize": 4,
    "group": "mjin_wood",
    "cookingBookCategory": "MISC",
    "xpReward": 0.0,
    "cookingTime": 200,
    "craftingBookCategory": "BUILDING",
    "recipeShapeless": false,
    "recipeSlots": [
      {
        "value": "CUSTOM:MjinLog"
      },
      {
        "value": "CUSTOM:MjinLog"
      },
      {
        "value": ""
      },
      {
        "value": "CUSTOM:MjinLog"
      },
      {
        "value": "CUSTOM:MjinLog"
      },
      {
        "value": ""
      },
      {
        "value": ""
      },
      {
        "value": ""
      },
      {
        "value": ""
      }
    ],
    "recipeReturnStack": {
      "value": "CUSTOM:MjinWood"
    },
    "name": "mjin_wood_recipe",
    "namespace": "mod"
  }
}